transaction_balance_analyzer/__init__.py
transaction_balance_analyzer/analyzer.py
transaction_balance_analyzer/data/ABC_token_data.csv
transaction_balance_analyzer/data/default_abi.json
transaction_balance_analyzer/utils/__init__.py
transaction_balance_analyzer/utils/config.py
transaction_balance_analyzer/utils/conversion.py
transaction_balance_analyzer/utils/token_utils.py
transaction_balance_analyzer-0.1.0.dist-info/LICENSE
transaction_balance_analyzer-0.1.0.dist-info/METADATA
transaction_balance_analyzer-0.1.0.dist-info/WHEEL
transaction_balance_analyzer-0.1.0.dist-info/top_level.txt
transaction_balance_analyzer-0.1.0.dist-info/RECORD
