Metadata-Version: 2.2
Name: transaction_balance_analyzer
Version: 0.1.0
Summary: A tool for analyzing account balance changes in Ethereum transactions
Home-page: https://github.com/yourusername/transaction_balance_analyzer
Author: Tao Yan, Guanda Zhao, Claudio J.Tessone
Author-email: yan@ifi.uzh.ch, guanda.zhao@uzh.ch, claudio.tessone@uzh.ch
Classifier: Development Status :: 3 - Alpha
Classifier: Intended Audience :: Developers
Classifier: License :: OSI Approved :: MIT License
Classifier: Programming Language :: Python :: 3
Classifier: Programming Language :: Python :: 3.7
Requires-Python: >=3.7
License-File: LICENSE
Requires-Dist: web3>=6.0.0
Requires-Dist: pandas>=1.3.0
Requires-Dist: requests>=2.25.0
Requires-Dist: tqdm>=4.65.0
Dynamic: author
Dynamic: author-email
Dynamic: classifier
Dynamic: description
Dynamic: description-content-type
Dynamic: home-page
Dynamic: requires-dist
Dynamic: requires-python
Dynamic: summary
